setup.py
modellogging/__init__.py
modellogging.egg-info/PKG-INFO
modellogging.egg-info/SOURCES.txt
modellogging.egg-info/dependency_links.txt
modellogging.egg-info/not-zip-safe
modellogging.egg-info/requires.txt
modellogging.egg-info/top_level.txt