Metadata-Version: 1.0
Name: modellogging
Version: 1.0
Summary: Easily configured logging.
Home-page: http://github.com/cidrblock/modellogging
Author: Bradley A. Thornton
Author-email: brad@thethorntons.net
License: MIT
Platform: UNKNOWN
